inflex/__init__.py
inflex/adjective.py
inflex/adjective_core.py
inflex/indefinite_core.py
inflex/noun.py
inflex/noun_core.py
inflex/syllable.py
inflex/term.py
inflex/verb.py
inflex/verb_core.py
inflex/data/cmudict_stress.json
inflex-1.0.6.dist-info/LICENSE
inflex-1.0.6.dist-info/METADATA
inflex-1.0.6.dist-info/WHEEL
inflex-1.0.6.dist-info/top_level.txt
inflex-1.0.6.dist-info/RECORD
