Metadata-Version: 2.1
Name: inflex
Version: 1.0.6
Summary: Inflection (conjugation and declension) of the English Language.
Home-page: https://github.com/tomaarsen/inflex
Author: Tom Aarsen
Author-email: cubiegamedev@gmail.com
License: MIT
Platform: UNKNOWN
Classifier: License :: OSI Approved :: MIT License
Classifier: Programming Language :: Python
Classifier: Programming Language :: Python :: 3
Classifier: Programming Language :: Python :: 3.6
Classifier: Programming Language :: Python :: 3.7
Classifier: Programming Language :: Python :: 3.8
Classifier: Programming Language :: Python :: 3.9
Classifier: Programming Language :: Python :: Implementation :: CPython
Classifier: Programming Language :: Python :: Implementation :: PyPy
Requires-Python: >=3.6.0
